greenlet-3.1.0.dist-info/LICENSE
greenlet-3.1.0.dist-info/LICENSE.PSF
greenlet-3.1.0.dist-info/METADATA
greenlet-3.1.0.dist-info/top_level.txt
greenlet-3.1.0.dist-info/RECORD
greenlet-3.1.0.dist-info/WHEEL
greenlet-3.1.0.dist-info/AUTHORS
greenlet-3.1.0.data/headers/greenlet.h
greenlet/TBrokenGreenlet.cpp
greenlet/greenlet_cpython_add_pending.hpp
greenlet/greenlet_thread_state_dict_cleanup.hpp
greenlet/greenlet_internal.hpp
greenlet/greenlet.cpp
greenlet/greenlet_thread_state.hpp
greenlet/TThreadStateDestroy.cpp
greenlet/TUserGreenlet.cpp
greenlet/greenlet_greenlet.hpp
greenlet/greenlet_cpython_compat.hpp
greenlet/TGreenlet.cpp
greenlet/greenlet_allocator.hpp
greenlet/greenlet_slp_switch.hpp
greenlet/TPythonState.cpp
greenlet/greenlet_exceptions.hpp
greenlet/greenlet_compiler_compat.hpp
greenlet/slp_platformselect.h
greenlet/__init__.py
greenlet/TExceptionState.cpp
greenlet/TStackState.cpp
greenlet/greenlet.h
greenlet/greenlet_refs.hpp
greenlet/TMainGreenlet.cpp
greenlet/_greenlet.cpython-310-s390x-linux-gnu.so
greenlet/greenlet_thread_support.hpp
greenlet/TGreenletGlobals.cpp
greenlet/tests/test_version.py
greenlet/tests/test_greenlet.py
greenlet/tests/test_generator_nested.py
greenlet/tests/fail_switch_two_greenlets.py
greenlet/tests/_test_extension_cpp.cpp
greenlet/tests/test_gc.py
greenlet/tests/test_generator.py
greenlet/tests/fail_cpp_exception.py
greenlet/tests/test_greenlet_trash.py
greenlet/tests/test_contextvars.py
greenlet/tests/leakcheck.py
greenlet/tests/_test_extension.cpython-310-s390x-linux-gnu.so
greenlet/tests/fail_clearing_run_switches.py
greenlet/tests/test_tracing.py
greenlet/tests/test_stack_saved.py
greenlet/tests/fail_initialstub_already_started.py
greenlet/tests/fail_switch_three_greenlets.py
greenlet/tests/_test_extension.c
greenlet/tests/fail_slp_switch.py
greenlet/tests/__init__.py
greenlet/tests/test_leaks.py
greenlet/tests/test_extension_interface.py
greenlet/tests/test_throw.py
greenlet/tests/test_weakref.py
greenlet/tests/test_cpp.py
greenlet/tests/fail_switch_three_greenlets2.py
greenlet/tests/_test_extension_cpp.cpython-310-s390x-linux-gnu.so
greenlet/platform/switch_sparc_sun_gcc.h
