Metadata-Version: 2.1
Name: greenlet
Version: 3.1.0
Summary: Lightweight in-process concurrent programming
Home-page: https://greenlet.readthedocs.io/
Author: Alexey Borzenkov
Author-email: snaury@gmail.com
Maintainer: Jason Madden
Maintainer-email: jason@seecoresoftware.com
License: MIT License
Project-URL: Bug Tracker, https://github.com/python-greenlet/greenlet/issues
Project-URL: Source Code, https://github.com/python-greenlet/greenlet/
Project-URL: Documentation, https://greenlet.readthedocs.io/
Keywords: greenlet coroutine concurrency threads cooperative
Platform: any
Classifier: Development Status :: 5 - Production/Stable
Classifier: Intended Audience :: Developers
Classifier: License :: OSI Approved :: MIT License
Classifier: Natural Language :: English
Classifier: Programming Language :: C
Classifier: Programming Language :: Python
Classifier: Programming Language :: Python :: 3
Classifier: Programming Language :: Python :: 3 :: Only
Classifier: Programming Language :: Python :: 3.7
Classifier: Programming Language :: Python :: 3.8
Classifier: Programming Language :: Python :: 3.9
Classifier: Programming Language :: Python :: 3.10
Classifier: Programming Language :: Python :: 3.11
Classifier: Programming Language :: Python :: 3.12
Classifier: Programming Language :: Python :: 3.13
Classifier: Operating System :: OS Independent
Classifier: Topic :: Software Development :: Libraries :: Python Modules
Requires-Python: >=3.7
License-File: LICENSE
License-File: LICENSE.PSF
License-File: AUTHORS
Provides-Extra: docs
Requires-Dist: Sphinx; extra == "docs"
Requires-Dist: furo; extra == "docs"
Provides-Extra: test
Requires-Dist: objgraph; extra == "test"
Requires-Dist: psutil; extra == "test"
